signxai/examples/__init__.py
signxai/examples/mnist.py
signxai/examples/vgg16.py
signxai/methods/__init__.py
signxai/methods/grad_cam.py
signxai/methods/guided_backprop.py
signxai/methods/signed.py
signxai/methods/wrappers.py
signxai/methods/innvestigate/__init__.py
signxai/methods/innvestigate/layers.py
signxai/methods/innvestigate/analyzer/__init__.py
signxai/methods/innvestigate/analyzer/base.py
signxai/methods/innvestigate/analyzer/deeplift.py
signxai/methods/innvestigate/analyzer/deeptaylor.py
signxai/methods/innvestigate/analyzer/gradient_based.py
signxai/methods/innvestigate/analyzer/misc.py
signxai/methods/innvestigate/analyzer/pattern_based.py
signxai/methods/innvestigate/analyzer/reverse_map.py
signxai/methods/innvestigate/analyzer/wrapper.py
signxai/methods/innvestigate/analyzer/canonization/__init__.py
signxai/methods/innvestigate/analyzer/relevance_based/__init__.py
signxai/methods/innvestigate/analyzer/relevance_based/relevance_analyzer.py
signxai/methods/innvestigate/analyzer/relevance_based/relevance_rule_base.py
signxai/methods/innvestigate/analyzer/relevance_based/utils.py
signxai/methods/innvestigate/applications/__init__.py
signxai/methods/innvestigate/applications/imagenet.py
signxai/methods/innvestigate/applications/mnist.py
signxai/methods/innvestigate/backend/__init__.py
signxai/methods/innvestigate/backend/tensorflow.py
signxai/methods/innvestigate/backend/torch.py
signxai/methods/innvestigate/tests/__init__.py
signxai/methods/innvestigate/tests/analyzer/__init__.py
signxai/methods/innvestigate/tests/analyzer/test_base.py
signxai/methods/innvestigate/tests/analyzer/test_deeplift.py
signxai/methods/innvestigate/tests/analyzer/test_deeptaylor.py
signxai/methods/innvestigate/tests/analyzer/test_gradient_based.py
signxai/methods/innvestigate/tests/analyzer/test_init.py
signxai/methods/innvestigate/tests/analyzer/test_misc.py
signxai/methods/innvestigate/tests/analyzer/test_pattern_based.py
signxai-1.1.9.2.dist-info/LICENSE
signxai-1.1.9.2.dist-info/METADATA
signxai-1.1.9.2.dist-info/WHEEL
signxai-1.1.9.2.dist-info/top_level.txt
signxai-1.1.9.2.dist-info/RECORD
