Metadata-Version: 2.1
Name: signxai
Version: 1.1.9.2
Summary: SIGNed explanations: Unveiling relevant features by reducing bias
Home-page: https://github.com/nilsgumpfer/SIGN-XAI
Author: Nils Gumpfer
Author-email: nils.gumpfer@kite.thm.de
Maintainer: Nils Gumpfer
Maintainer-email: nils.gumpfer@kite.thm.de
License: BSD 2-Clause License
Keywords: XAI,SIGN,LRP
Classifier: Programming Language :: Python :: 3
Classifier: Operating System :: OS Independent
Classifier: License :: OSI Approved :: BSD License
Classifier: Development Status :: 5 - Production/Stable
Classifier: Environment :: Console
Classifier: Intended Audience :: Science/Research
Classifier: Topic :: Scientific/Engineering :: Artificial Intelligence
License-File: LICENSE
Requires-Dist: matplotlib >=3.7.0
Requires-Dist: scipy >=1.10.0
Requires-Dist: version-parser >=1.0.1
Requires-Dist: tensorflow-macos <=2.12.0,>=2.8.0 ; platform_system == "Darwin"
Requires-Dist: tensorflow <=2.12.1,>=2.8.0 ; platform_system == "Linux"
Requires-Dist: tensorflow <=2.12.1,>=2.8.0 ; platform_system == "Windows"
